plot/__init__.py
plot/config.py
plot/main.py
plotshell-0.1.1.dist-info/METADATA
plotshell-0.1.1.dist-info/WHEEL
plotshell-0.1.1.dist-info/entry_points.txt
plotshell-0.1.1.dist-info/top_level.txt
plotshell-0.1.1.dist-info/RECORD
