Metadata-Version: 2.1
Name: plotshell
Version: 0.1.1
Summary: AI helper for DevOps using OpenAI.
Home-page: https://plot.sh
Author: Sajith Amma
Author-email: sajith@tshaped.in
Requires-Dist: openai
Requires-Dist: configparser
Requires-Dist: distro
Requires-Dist: rich
